area_converter.py
area_converter-0.1.6.dist-info/METADATA
area_converter-0.1.6.dist-info/WHEEL
area_converter-0.1.6.dist-info/entry_points.txt
area_converter-0.1.6.dist-info/top_level.txt
area_converter-0.1.6.dist-info/RECORD
